quill/__init__.py
quill/enemy.py
quill/item.py
quill/loottable.py
quill/merchant.py
quill/player.py
quill/quest.py
quill/window.py
quill-1.10.0.dist-info/DESCRIPTION.rst
quill-1.10.0.dist-info/METADATA
quill-1.10.0.dist-info/RECORD
quill-1.10.0.dist-info/WHEEL
quill-1.10.0.dist-info/metadata.json
quill-1.10.0.dist-info/top_level.txt
