Metadata-Version: 2.0
Name: quill
Version: 1.10.0
Summary: A Python library used to create text-based games with TkInter.
Home-page: https://github.com/DeflatedPickle/adventure
Author: DeflatedPickle
Author-email: DeflatedPickle@gmail.com
License: MIT
Keywords: quill,text-based,adventure,game,GUI,window
Platform: UNKNOWN
Classifier: Intended Audience :: Developers
Classifier: License :: OSI Approved :: MIT License
Classifier: Programming Language :: Python :: 3.4
Classifier: Programming Language :: Python :: 3.5
